time_travel/__init__.py
time_travel/event_pool.py
time_travel/time_machine_clock.py
time_travel/time_travel.py
time_travel/patchers/__init__.py
time_travel/patchers/base_patcher.py
time_travel/patchers/datetime_patcher.py
time_travel/patchers/poll_patcher.py
time_travel/patchers/select_patcher.py
time_travel/patchers/time_patcher.py
time_travel-1.1.2.dist-info/METADATA
time_travel-1.1.2.dist-info/RECORD
time_travel-1.1.2.dist-info/WHEEL
time_travel-1.1.2.dist-info/entry_points.txt
time_travel-1.1.2.dist-info/top_level.txt
